civet/__init__.py
civet/abstract_data.py
civet/bases.py
civet/globals.py
civet/memoization.py
civet/minc.py
civet/obj.py
civet/shells.py
civet/xfm.py
civet/extraction/__init__.py
civet/extraction/hemisphere.py
civet/extraction/side.py
civet/extraction/starting_models.py
civet/extraction/surfaces.py
civet/extraction/kernels/__init__.py
civet/extraction/kernels/data/ngh_count.kernel
pycivet-0.1.2.data/scripts/interpolate_surface_with_sphere.pl
pycivet-0.1.2.data/scripts/mincblur_correct_name.sh
pycivet-0.1.2.data/scripts/mincreshape_bbox_helper
pycivet-0.1.2.dist-info/LICENSE
pycivet-0.1.2.dist-info/METADATA
pycivet-0.1.2.dist-info/WHEEL
pycivet-0.1.2.dist-info/top_level.txt
pycivet-0.1.2.dist-info/RECORD
