Metadata-Version: 2.1
Name: pycivet
Version: 0.1.2
Summary: Object-oriented CIVET bindings for Python
Home-page: https://github.com/FNNDSC/pycivet
Author: Jennings Zhang
Author-email: Jennings.Zhang@childrens.harvard.edu
License: MIT
Project-URL: Documentation, https://fnndsc.github.io/pycivet/
Project-URL: Source, https://github.com/FNNDSC/pycivet
Project-URL: Tracker, https://github.com/FNNDSC/pycivet/issues
Classifier: License :: OSI Approved :: MIT License
Classifier: Programming Language :: Python :: 3.10
Classifier: Topic :: Scientific/Engineering
Classifier: Topic :: Scientific/Engineering :: Bio-Informatics
Classifier: Topic :: Scientific/Engineering :: Medical Science Apps.
Requires-Python: >=3.10.2
License-File: LICENSE
